abbrfix/__init__.py
abbrfix/abbr.py
abbrfix/abbreviations.json
abbrfix-26.2.2024.dist-info/LICENSE
abbrfix-26.2.2024.dist-info/METADATA
abbrfix-26.2.2024.dist-info/WHEEL
abbrfix-26.2.2024.dist-info/top_level.txt
abbrfix-26.2.2024.dist-info/RECORD
