Metadata-Version: 2.1
Name: abbrfix
Version: 26.2.2024
Summary: Expand and collapse abbreviations commonly used in online communication
Home-page: https://github.com/dsymbol/abbrfix
Author: dsymbol
License: OSI Approved :: MIT License
Classifier: Programming Language :: Python :: 3
Classifier: License :: OSI Approved :: MIT License
License-File: LICENSE
